w6libs/__init__.py
w6libs/pdf_extract.py
w6libs/PyPDF2/__init__.py
w6libs/PyPDF2/_cmap.py
w6libs/PyPDF2/_codecs/__init__.py
w6libs/PyPDF2/_codecs/adobe_glyphs.py
w6libs/PyPDF2/_codecs/pdfdoc.py
w6libs/PyPDF2/_codecs/std.py
w6libs/PyPDF2/_codecs/symbol.py
w6libs/PyPDF2/_codecs/zapfding.py
w6libs/PyPDF2/_encryption.py
w6libs/PyPDF2/_merger.py
w6libs/PyPDF2/_page.py
w6libs/PyPDF2/_reader.py
w6libs/PyPDF2/_security.py
w6libs/PyPDF2/_utils.py
w6libs/PyPDF2/_version.py
w6libs/PyPDF2/_writer.py
w6libs/PyPDF2/constants.py
w6libs/PyPDF2/errors.py
w6libs/PyPDF2/filters.py
w6libs/PyPDF2/generic/__init__.py
w6libs/PyPDF2/generic/_annotations.py
w6libs/PyPDF2/generic/_base.py
w6libs/PyPDF2/generic/_data_structures.py
w6libs/PyPDF2/generic/_outline.py
w6libs/PyPDF2/generic/_rectangle.py
w6libs/PyPDF2/generic/_utils.py
w6libs/PyPDF2/pagerange.py
w6libs/PyPDF2/papersizes.py
w6libs/PyPDF2/py.typed
w6libs/PyPDF2/types.py
w6libs/PyPDF2/xmp.py
w6_libs-0.0.4.dist-info/LICENSE
w6_libs-0.0.4.dist-info/WHEEL
w6_libs-0.0.4.dist-info/METADATA
w6_libs-0.0.4.dist-info/RECORD
